unilookup/__init__.py
unilookup/unilookup.py
unilookup-0.1.1.dist-info/LICENSE
unilookup-0.1.1.dist-info/METADATA
unilookup-0.1.1.dist-info/WHEEL
unilookup-0.1.1.dist-info/entry_points.txt
unilookup-0.1.1.dist-info/RECORD
