Metadata-Version: 2.1
Name: unilookup
Version: 0.1.1
Summary: A simple CLI Python utility for looking up unicode codepoints
License: GPL-3.0-or-later
Author: Martin Maciaszek
Author-email: martin@maciaszek.net
Requires-Python: >=3.10,<4.0
Classifier: License :: OSI Approved :: GNU General Public License v3 or later (GPLv3+)
Classifier: Programming Language :: Python :: 3
Classifier: Programming Language :: Python :: 3.10
Classifier: Programming Language :: Python :: 3.11
Classifier: Programming Language :: Python :: 3.12
Requires-Dist: terminaltables (>=3.1.10,<4.0.0)
Requires-Dist: unicodedata2 (>=15.1.0,<16.0.0)
